insurance_gi/__init__.py
insurance_gi/claims.py
insurance_gi/decrements.py
insurance_gi/financials.py
insurance_gi/renewals.py
insurance_gi-0.0.4.dist-info/LICENSE
insurance_gi-0.0.4.dist-info/METADATA
insurance_gi-0.0.4.dist-info/WHEEL
insurance_gi-0.0.4.dist-info/top_level.txt
insurance_gi-0.0.4.dist-info/RECORD
